aitool/__init__.py
aitool/config.py
aitool/r0_standard/__init__.py
aitool/r0_standard/cache.py
aitool/r0_standard/deduplication.py
aitool/r0_standard/dict_op.py
aitool/r0_standard/list_op.py
aitool/r0_standard/path.py
aitool/r0_standard/print_op.py
aitool/r0_standard/random_op.py
aitool/r0_standard/re_op.py
aitool/r0_standard/retry.py
aitool/r0_standard/scoring.py
aitool/r0_standard/security.py
aitool/r0_standard/singleton.py
aitool/r0_standard/string_op.py
aitool/r0_standard/time_op.py
aitool/r1_basic/__init__.py
aitool/r1_basic/conda.py
aitool/r1_basic/distribution.py
aitool/r1_basic/download.py
aitool/r1_basic/file.py
aitool/r1_basic/format_data.py
aitool/r1_basic/log_tool.py
aitool/r1_basic/multi.py
aitool/r1_basic/pip_tool.py
aitool/r1_basic/shell.py
aitool/r1_basic/word.py
aitool/r2_structure/__init__.py
aitool/r2_structure/arithmetic/__init__.py
aitool/r2_structure/arithmetic/dfs_search.py
aitool/r2_structure/arithmetic/name.py
aitool/r2_structure/graph/__init__.py
aitool/r2_structure/graph/chain_forward_stars.py
aitool/r2_structure/interview/__init__.py
aitool/r2_structure/interview/f-sort.py
aitool/r2_structure/interview/pytorch_demo_1.py
aitool/r2_structure/interview/pytorch_demo_2.py
aitool/r2_structure/interview/sort.py
aitool/r2_structure/interview/sum_two_number.py
aitool/r2_structure/interview/tensorflow_demo_1.py
aitool/r2_structure/interview/tensorflow_demo_2.py
aitool/r2_structure/interview/tensorflow_demo_3.py
aitool/r2_structure/interview/tensorflow_demo_4.py
aitool/r2_structure/interview/transformer.py
aitool/r2_structure/interview/try2.py
aitool/r2_structure/interview/try3.py
aitool/r2_structure/interview/try4.py
aitool/r3_datasets/__init__.py
aitool/r3_datasets/negative.txt
aitool/r3_datasets/positive.txt
aitool/r3_datasets/stopwords.txt
aitool/r4_algorithm/__init__.py
aitool/r4_algorithm/basic/__init__.py
aitool/r4_algorithm/basic/conditional_probability.py
aitool/r4_algorithm/basic/ngram_tf_idf.py
aitool/r4_algorithm/basic/ngram_tfidf.py
aitool-0.0.294.dist-info/LICENSE
aitool-0.0.294.dist-info/METADATA
aitool-0.0.294.dist-info/WHEEL
aitool-0.0.294.dist-info/top_level.txt
aitool-0.0.294.dist-info/RECORD
